signalboard/__init__.py
signalboard/api.py
signalboard/cli.py
signalboard/main.py
signalboard/security.py
signalboard/static.py
signalboard/modules/__init__.py
signalboard/modules/classifier/__init__.py
signalboard/modules/classifier/model.py
signalboard/modules/classifier/router.py
signalboard/modules/dataset/__init__.py
signalboard/modules/dataset/model.py
signalboard/modules/dataset/router.py
signalboard/modules/health/__init__.py
signalboard/modules/health/model.py
signalboard/modules/health/router.py
signalboard/shared/__init__.py
signalboard/shared/model.py
signalboard/shared/schema.py
signalboard/shared/type.py
signalboard-0.0.0.dist-info/AUTHORS.rst
signalboard-0.0.0.dist-info/LICENSE
signalboard-0.0.0.dist-info/METADATA
signalboard-0.0.0.dist-info/WHEEL
signalboard-0.0.0.dist-info/entry_points.txt
signalboard-0.0.0.dist-info/top_level.txt
signalboard-0.0.0.dist-info/RECORD
