Metadata-Version: 2.1
Name: signalboard
Version: 0.0.0
Summary: Board for River library
Home-page: https://github.com/sylwekczmil/signalboard
Author: Sylwester Czmil
Author-email: sylwekczmil@gmail.com
License: BSD license
Keywords: signalboard
Platform: UNKNOWN
Classifier: Development Status :: 2 - Pre-Alpha
Classifier: Intended Audience :: Developers
Classifier: License :: OSI Approved :: BSD License
Classifier: Natural Language :: English
Classifier: Programming Language :: Python :: 3
Classifier: Programming Language :: Python :: 3.6
Classifier: Programming Language :: Python :: 3.7
Classifier: Programming Language :: Python :: 3.8
Requires-Python: >=3.6
License-File: LICENSE
License-File: AUTHORS.rst
Requires-Dist: aiofiles (==0.7.0)
Requires-Dist: Click (==8.0.3)
Requires-Dist: fastapi (==0.70.0)
Requires-Dist: pandas (==1.3.4)
Requires-Dist: pydantic (==1.8.2)
Requires-Dist: river (==0.10.1)
Requires-Dist: uvicorn[standard] (==0.15.0)
